README.md
setup.py
ceotr_common_utilities/__init__.py
ceotr_common_utilities/dataset_id_generate_function.py
ceotr_common_utilities/file_prepare.py
ceotr_common_utilities/gps_points_tools.py
ceotr_common_utilities/list_compare.py
ceotr_common_utilities/os_function.py
ceotr_common_utilities/string_tools.py
ceotr_common_utilities/time_format_functions.py
ceotr_common_utilities.egg-info/PKG-INFO
ceotr_common_utilities.egg-info/SOURCES.txt
ceotr_common_utilities.egg-info/dependency_links.txt
ceotr_common_utilities.egg-info/requires.txt
ceotr_common_utilities.egg-info/top_level.txt
ceotr_common_utilities.egg-info/zip-safe