Metadata-Version: 1.0
Name: ceotr-common-utilities
Version: 1.0.4
Summary: Common Python
Home-page: https://gitlab.oceantrack.org/ceotr-public/ceotr_app_common/ceotr_common_utilities
Author: CEOTR
Author-email: support@ceotr.ca
License: GNU General Public License v3 (GPLv3)
Platform: UNKNOWN
